changecrab/__init__.py
changecrab/client.py
changecrab/exceptions.py
changecrab/models.py
changecrab/py.typed
changecrab-0.1.1.dist-info/licenses/LICENSE
changecrab-0.1.1.dist-info/METADATA
changecrab-0.1.1.dist-info/WHEEL
changecrab-0.1.1.dist-info/top_level.txt
changecrab-0.1.1.dist-info/RECORD
