Metadata-Version: 2.4
Name: changecrab
Version: 0.1.1
Summary: Official Python SDK for the ChangeCrab API
Author-email: ChangeCrab <support@changecrab.com>
License: MIT
Project-URL: Homepage, https://changecrab.com
Project-URL: Documentation, https://changecrab.com/api/docs
Project-URL: Repository, https://github.com/changecrab/python_sdk
Project-URL: Issues, https://github.com/changecrab/python_sdk/issues
Keywords: changecrab,changelog,api,sdk,release-notes
Classifier: Development Status :: 5 - Production/Stable
Classifier: Intended Audience :: Developers
Classifier: License :: OSI Approved :: MIT License
Classifier: Operating System :: OS Independent
Classifier: Programming Language :: Python :: 3
Classifier: Programming Language :: Python :: 3.8
Classifier: Programming Language :: Python :: 3.9
Classifier: Programming Language :: Python :: 3.10
Classifier: Programming Language :: Python :: 3.11
Classifier: Programming Language :: Python :: 3.12
Classifier: Topic :: Software Development :: Libraries :: Python Modules
Classifier: Typing :: Typed
Requires-Python: >=3.8
License-File: LICENSE
Requires-Dist: requests>=2.28.0
Provides-Extra: dev
Requires-Dist: pytest>=7.0.0; extra == "dev"
Requires-Dist: pytest-cov>=4.0.0; extra == "dev"
Requires-Dist: responses>=0.23.0; extra == "dev"
Requires-Dist: mypy>=1.0.0; extra == "dev"
Requires-Dist: ruff>=0.1.0; extra == "dev"
Dynamic: license-file
